takeltest/__init__.py
takeltest/ansibleres.py
takeltest/ansiblerun.py
takeltest/boilerplate.py
takeltest/exceptions.py
takeltest/jsonvars.py
takeltest/moleculebook.py
takeltest/moleculeenv.py
takeltest/moleculelog.py
takeltest/moleculeplay.py
takeltest/multitestvars.py
takeltest/pathlist.py
takeltest/plugin.py
takeltest/templates.py
takeltest/testpass.py
takeltest-0.8.0.dist-info/LICENSE
takeltest-0.8.0.dist-info/METADATA
takeltest-0.8.0.dist-info/WHEEL
takeltest-0.8.0.dist-info/entry_points.txt
takeltest-0.8.0.dist-info/top_level.txt
takeltest-0.8.0.dist-info/RECORD
