Metadata-Version: 2.1
Name: takeltest
Version: 0.8.0
Summary: Fixtures for ansible, testinfra and molecule
Home-page: https://github.com/geospin-takelage/takelage-var
Author: Geospin
Author-email: takelage@geospin.de
License: GPLv3
Platform: any
Classifier: Programming Language :: Python
Classifier: Programming Language :: Python :: 3
Classifier: Intended Audience :: Information Technology
Classifier: Intended Audience :: Developers
Classifier: Intended Audience :: System Administrators
Classifier: License :: OSI Approved :: MIT License
Classifier: Operating System :: POSIX
Classifier: Topic :: Software Development :: Libraries :: Python Modules
Classifier: Topic :: Software Development :: Testing
Classifier: Topic :: System :: Systems Administration
Classifier: Framework :: Pytest
Requires-Dist: ansible (>=2.8)
